purplship/mappers/usps/__init__.py
purplship/mappers/usps/mapper.py
purplship/mappers/usps/proxy.py
purplship/mappers/usps/settings.py
purplship/providers/usps/__init__.py
purplship/providers/usps/error.py
purplship/providers/usps/pickup/__init__.py
purplship/providers/usps/pickup/cancel.py
purplship/providers/usps/pickup/create.py
purplship/providers/usps/pickup/update.py
purplship/providers/usps/rate.py
purplship/providers/usps/shipment/__init__.py
purplship/providers/usps/shipment/cancel.py
purplship/providers/usps/shipment/create.py
purplship/providers/usps/tracking.py
purplship/providers/usps/units.py
purplship/providers/usps/utils.py
purplship.usps-2022.2.dist-info/WHEEL
purplship.usps-2022.2.dist-info/METADATA
purplship.usps-2022.2.dist-info/RECORD
